__init__.py
data_loader.py
database.py
server.py
ciqual_mcp-0.2.0.dist-info/licenses/LICENSE
ciqual_mcp-0.2.0.dist-info/METADATA
ciqual_mcp-0.2.0.dist-info/WHEEL
ciqual_mcp-0.2.0.dist-info/entry_points.txt
ciqual_mcp-0.2.0.dist-info/top_level.txt
ciqual_mcp-0.2.0.dist-info/RECORD
