Metadata-Version: 2.4
Name: ciqual-mcp
Version: 0.2.0
Summary: MCP server for ANSES Ciqual French food composition database with SQL interface
Author-email: Gael Debost <gael@ideagency.fr>
License: MIT
Project-URL: Homepage, https://github.com/zzgael/ciqual-mcp
Project-URL: Bug Reports, https://github.com/zzgael/ciqual-mcp/issues
Project-URL: Source, https://github.com/zzgael/ciqual-mcp
Keywords: mcp,ciqual,anses,nutrition,food,database,sql
Classifier: Development Status :: 4 - Beta
Classifier: Intended Audience :: Developers
Classifier: License :: OSI Approved :: MIT License
Classifier: Programming Language :: Python :: 3
Classifier: Programming Language :: Python :: 3.10
Classifier: Programming Language :: Python :: 3.11
Classifier: Programming Language :: Python :: 3.12
Classifier: Topic :: Database
Classifier: Topic :: Scientific/Engineering :: Information Analysis
Classifier: Topic :: Software Development :: Libraries :: Python Modules
Requires-Python: >=3.10
License-File: LICENSE
Requires-Dist: fastmcp>=0.1.0
Requires-Dist: lxml>=4.9.0
Provides-Extra: dev
Requires-Dist: pytest>=7.0.0; extra == "dev"
Requires-Dist: pytest-asyncio>=0.21.0; extra == "dev"
Dynamic: license-file
